cookiejar/__init__.py
cookiejar/channel.py
cookiejar/client.py
cookiejar/creator.py
cookiejar/downloader.py
cookiejar/extractor.py
cookiejar/jar.py
cookiejar/loaders.py
cookiejar/pager.py
cookiejar/settings.py
cookiejar/utils.py
cookiejar-0.0.2.data/scripts/cookiejar
cookiejar-0.0.2.dist-info/METADATA
cookiejar-0.0.2.dist-info/RECORD
cookiejar-0.0.2.dist-info/WHEEL
cookiejar-0.0.2.dist-info/top_level.txt
