Metadata-Version: 2.1
Name: cookiejar
Version: 0.0.2
Summary: Cookiecutter templates discovery and management.
Home-page: https://github.com/fcurella/cookiejar
Author: Flavio Curella
Author-email: flavio.curella@gmail.com
License: MIT
Platform: UNKNOWN
Classifier: Development Status :: 3 - Alpha
Classifier: Environment :: Console
Classifier: Intended Audience :: Developers
Classifier: Intended Audience :: Information Technology
Classifier: License :: OSI Approved :: MIT License
Classifier: Operating System :: OS Independent
Classifier: Programming Language :: Python
Classifier: Programming Language :: Python :: 2
Classifier: Programming Language :: Python :: 2.7
Classifier: Programming Language :: Python :: 3
Classifier: Programming Language :: Python :: 3.4
Classifier: Programming Language :: Python :: 3.5
Classifier: Programming Language :: Python :: 3.6
Requires-Dist: argparse
Requires-Dist: pager
Requires-Dist: cookiecutter
